PlainTools.py
PlainToolsDocs.html
__init__.py
plaintools-1.3.241226.0.dist-info/METADATA
plaintools-1.3.241226.0.dist-info/WHEEL
plaintools-1.3.241226.0.dist-info/licenses/LICENSE
plaintools-1.3.241226.0.dist-info/RECORD
