Metadata-Version: 2.4
Name: PlainTools
Version: 1.3.241226.0
Summary: A library designed to streamline simple operations, loops and contexts.
Project-URL: Homepage, https://github.com/gabrielmsilva00/PlainTools
Project-URL: Issues, https://github.com/gabrielmsilva00/PlainTools/issues
Author-email: Gabriel Maia <gabrielmaia.silva00@gmail.com>
License-File: LICENSE
Classifier: License :: OSI Approved :: MIT License
Classifier: Operating System :: OS Independent
Classifier: Programming Language :: Python :: 3
Requires-Python: >=3.11
